container_tools/__init__.py
container_tools/devcontainer.py
container_tools-0.1.0.dist-info/licenses/LICENSE
container_tools-0.1.0.dist-info/METADATA
container_tools-0.1.0.dist-info/WHEEL
container_tools-0.1.0.dist-info/top_level.txt
container_tools-0.1.0.dist-info/RECORD
