Metadata-Version: 2.4
Name: container_tools
Version: 0.1.0
Summary: Tools for parsing container files
Author: Seweryn Rusecki
License: MIT License
Project-URL: Homepage, https://github.com/serweryn617/container-tools
Project-URL: Issues, https://github.com/serweryn617/container-tools/issues
Classifier: Development Status :: 4 - Beta
Classifier: Environment :: Console
Classifier: Intended Audience :: Developers
Classifier: Topic :: Software Development :: Libraries
Classifier: Programming Language :: Python :: 3
Classifier: Programming Language :: Python :: 3.10
Classifier: Programming Language :: Python :: 3.11
Classifier: Programming Language :: Python :: 3.12
Classifier: License :: OSI Approved :: MIT License
Classifier: Operating System :: POSIX :: Linux
Requires-Python: >=3.10
License-File: LICENSE
Dynamic: license-file
